Workbook

Sheet 00_Anleitung
A1: SOLIDWORKS Costing – Startwerte Deutschland 2026
A3: Zweck | B3: Startdatensatz zum Befüllen leerer Costing-Vorlagen (.sldctm / .sldcts / .sldctc). Alle Werte sind marktübliche Richtwerte und müssen an eure Kostenstellenrechnung angeglichen werden.
A4: So einspielen | B4: 1) Costing-Vorlagen-Editor öffnen 2) Vorlage > 'Export nach Excel' 3) Werte aus dieser Mappe in die exportierte Datei übertragen (Spalten zuordnen) 4) 'Import' zurück in die Vorlage 5) speichern und mit Referenzteilen kalibrieren.
A5: Wichtig | B5: Diese Datei ist NICHT direkt importierbar – SOLIDWORKS erwartet seine eigene Spaltenstruktur, die sich je Version und Sprachstand unterscheidet. Immer erst exportieren, dann füllen.
A6: Was nicht per Excel geht | B6: Maschinenstundensätze, Rüstzeiten und benutzerdefinierte Operationen werden im Vorlagen-Editor eingetragen (Blätter 20, 21, 50 dieser Mappe).
A8: LEGENDE
A9: blaue Zahl | B9: Eingabewert – hier anpassen
A10: schwarze Zahl | B10: Formel – nicht überschreiben
A11: gelbe Zelle | B11: zentrale Annahme, die viele Ergebnisse beeinflusst
A12: Hinweis zu Formeln | B12: Die berechneten Spalten (schwarz) werden beim ersten Öffnen in Excel automatisch berechnet; in Vorschau-Tools können sie vorher leer erscheinen.
A14: BLÄTTER
A15: 10_Material_Zerspanung | B15: Werkstoffe, Preis pro kg, Dichte, Schrotterlös – für die Zerspanungsvorlage
A16: 11_Material_Blech | B16: Werkstoff × Blechdicke, Tafelformate, Tafelpreise – für die Blechvorlage
A17: 20_Maschinen_Stundensaetze | B17: Stundensätze je Verfahren, Basis für alle abgeleiteten Kosten
A18: 21_Ruestzeiten | B18: Rüstzeiten je Los und daraus berechnete Rüstkosten
A19: 30_Zerspanung_MRR | B19: Zeitspanvolumen und Bohrvorschübe je Materialklasse
A20: 40_Laser_Schnittwerte | B20: Schnittgeschwindigkeiten, Einstechzeiten, Schnittkosten je Meter
A21: 41_Biegen | B21: Biegezeiten und Kosten je Biegung
A22: 50_Custom_Operationen | B22: Oberfläche, Prüfung, Verpackung – Register 'Benutzerdefiniert'
A23: 60_Aufschlaege | B23: Ausschuss, Gemeinkosten, Gewinn
A25: Stand | B25: August 2026
A26: Quellen | B26: siehe README.md im selben Ordner (Kapitel 7)

Sheet 10_Material_Zerspanung
A1: Materialdaten für die Zerspanungsvorlage (.sldctm)
A2: Preise = Handelsware, Klein-/Mittelmengen inkl. Zuschnittaufschlag, Stand 2026. Werkstoffname muss exakt dem Namen in eurer SOLIDWORKS-Werkstoffdatenbank entsprechen.
A4: Materialklasse | B4: Werkstoff (Name in SOLIDWORKS) | C4: Dichte [kg/m³] | D4: Preis min [€/kg] | E4: Preis max [€/kg] | F4: Startwert [€/kg] | G4: Schrotterlös [€/kg] | H4: Preis je dm³ [€] | I4: Bemerkung
A5: Stahl | B5: S235JR | C5: 7850 | D5: 1.4 | E5: 1.9 | F5: 1.65 | G5: 0.15 | H5: =C5*F5/1000 | I5: Standard-Baustahl, Flach/Blech
A6: Stahl | B6: S355J2 | C6: 7850 | D6: 1.6 | E6: 2.1 | F6: 1.8 | G6: 0.15 | H6: =C6*F6/1000 | I6: höherfest, Schweißkonstruktionen
A7: Stahl | B7: DC01 | C7: 7850 | D7: 1.5 | E7: 2 | F7: 1.75 | G7: 0.15 | H7: =C7*F7/1000 | I7: kaltgewalzt, Feinblech
A8: Stahl | B8: DX51D+Z (verzinkt) | C8: 7850 | D8: 1.6 | E8: 2.2 | F8: 1.9 | G8: 0.12 | H8: =C8*F8/1000 | I8: Zinkauflage im Preis enthalten
A9: Stahl | B9: C45 / 1.0503 | C9: 7850 | D9: 1.7 | E9: 2.3 | F9: 1.95 | G9: 0.15 | H9: =C9*F9/1000 | I9: Wellen, Drehteile
A10: Stahl | B10: 11SMn30 (Automatenstahl) | C10: 7850 | D10: 1.9 | E10: 2.6 | F10: 2.2 | G10: 0.15 | H10: =C10*F10/1000 | I10: gute Zerspanbarkeit
A11: Stahl | B11: 42CrMo4 | C11: 7850 | D11: 2.2 | E11: 3 | F11: 2.5 | G11: 0.15 | H11: =C11*F11/1000 | I11: vergütet, Rundmaterial
A12: Stahl | B12: 16MnCr5 | C12: 7850 | D12: 2.1 | E12: 2.9 | F12: 2.4 | G12: 0.15 | H12: =C12*F12/1000 | I12: Einsatzstahl
A13: Edelstahl | B13: 1.4301 (X5CrNi18-10) | C13: 7900 | D13: 8 | E13: 13 | F13: 10.5 | G13: 1.2 | H13: =C13*F13/1000 | I13: V2A, Legierungszuschlag monatlich prüfen
A14: Edelstahl | B14: 1.4404 (X2CrNiMo17-12-2) | C14: 8000 | D14: 10 | E14: 15 | F14: 12.5 | G14: 1.4 | H14: =C14*F14/1000 | I14: V4A, seewasserbeständig
A15: Edelstahl | B15: 1.4571 | C15: 8000 | D15: 11 | E15: 16 | F15: 13.5 | G15: 1.4 | H15: =C15*F15/1000 | I15: titanstabilisiert
A16: Aluminium | B16: EN AW-5754 (AlMg3) | C16: 2660 | D16: 5.5 | E16: 8 | F16: 6.5 | G16: 1.1 | H16: =C16*F16/1000 | I16: Blech, gut umformbar/schweißbar
... A29: Titan | B29: Ti Grade 5 (TiAl6V4) | C29: 4430 | D29: 45 | E29: 85 | F29: 60 | G29: 6 | H29: =C29*F29/1000 | I29: Luftfahrt, sehr teuer
A31: Startwert = empfohlener Eintrag in der Costing-Vorlage. Preis je dm³ dient nur zur Plausibilitätsprüfung.
A32: Bei 1.4301/1.4404 macht der Legierungszuschlag bis zu 40 % des Preises aus – monatlich nachziehen.

Sheet 11_Material_Blech
A1: Materialdaten für die Blechvorlage (.sldcts)
A2: Jede Kombination aus Werkstoff und Dicke ist in der Vorlage eine eigene Zeile. Fehlt eine Dicke, wird das Teil nicht bewertet.
A4: Werkstoff | B4: Dicke [mm] | C4: Dichte [kg/m³] | D4: Preis [€/kg] | E4: Tafel Länge [mm] | F4: Tafel Breite [mm] | G4: Tafelgewicht [kg] | H4: Tafelpreis [€] | I4: Preis je m² [€] | J4: Schrotterlös [€/kg]
A5: S235JR | B5: 1 | C5: 7850 | D5: 1.65 | E5: 3000 | F5: 1500 | G5: =E5/1000*F5/1000*B5/1000*C5 | H5: =G5*D5 | I5: =H5/(E5/1000*F5/1000) | J5: 0.15
A6: S235JR | B6: 1.5 | C6: 7850 | D6: 1.65 | E6: 3000 | F6: 1500 | G6: =E6/1000*F6/1000*B6/1000*C6 | H6: =G6*D6 | I6: =H6/(E6/1000*F6/1000) | J6: 0.15
A7: S235JR | B7: 2 | C7: 7850 | D7: 1.65 | E7: 3000 | F7: 1500 | G7: =E7/1000*F7/1000*B7/1000*C7 | H7: =G7*D7 | I7: =H7/(E7/1000*F7/1000) | J7: 0.15
A8: S235JR | B8: 3 | C8: 7850 | D8: 1.65 | E8: 3000 | F8: 1500 | G8: =E8/1000*F8/1000*B8/1000*C8 | H8: =G8*D8 | I8: =H8/(E8/1000*F8/1000) | J8: 0.15
A9: S235JR | B9: 4 | C9: 7850 | D9: 1.65 | E9: 3000 | F9: 1500 | G9: =E9/1000*F9/1000*B9/1000*C9 | H9: =G9*D9 | I9: =H9/(E9/1000*F9/1000) | J9: 0.15
A10: S235JR | B10: 5 | C10: 7850 | D10: 1.65 | E10: 3000 | F10: 1500 | G10: =E10/1000*F10/1000*B10/1000*C10 | H10: =G10*D10 | I10: =H10/(E10/1000*F10/1000) | J10: 0.15
A11: S235JR | B11: 6 | C11: 7850 | D11: 1.65 | E11: 3000 | F11: 1500 | G11: =E11/1000*F11/1000*B11/1000*C11 | H11: =G11*D11 | I11: =H11/(E11/1000*F11/1000) | J11: 0.15
A12: S235JR | B12: 8 | C12: 7850 | D12: 1.65 | E12: 3000 | F12: 1500 | G12: =E12/1000*F12/1000*B12/1000*C12 | H12: =G12*D12 | I12: =H12/(E12/1000*F12/1000) | J12: 0.15
A13: S235JR | B13: 10 | C13: 7850 | D13: 1.65 | E13: 3000 | F13: 1500 | G13: =E13/1000*F13/1000*B13/1000*C13 | H13: =G13*D13 | I13: =H13/(E13/1000*F13/1000) | J13: 0.15
A14: S235JR | B14: 12 | C14: 7850 | D14: 1.65 | E14: 3000 | F14: 1500 | G14: =E14/1000*F14/1000*B14/1000*C14 | H14: =G14*D14 | I14: =H14/(E14/1000*F14/1000) | J14: 0.15
A15: S235JR | B15: 15 | C15: 7850 | D15: 1.65 | E15: 3000 | F15: 1500 | G15: =E15/1000*F15/1000*B15/1000*C15 | H15: =G15*D15 | I15: =H15/(E15/1000*F15/1000) | J15: 0.15
A16: S235JR | B16: 20 | C16: 7850 | D16: 1.65 | E16: 3000 | F16: 1500 | G16: =E16/1000*F16/1000*B16/1000*C16 | H16: =G16*D16 | I16: =H16/(E16/1000*F16/1000) | J16: 0.15
... A51: EN AW-5754 (AlMg3) | B51: 10 | C51: 2660 | D51: 6.5 | E51: 2000 | F51: 1000 | G51: =E51/1000*F51/1000*B51/1000*C51 | H51: =G51*D51 | I51: =H51/(E51/1000*F51/1000) | J51: 1.1
A53: Tafelgewicht/Tafelpreis sind berechnet – in der Vorlage werden je nach Version Tafelformat und €/kg eingetragen.
A54: Verschnitt bildet Costing über die Schachtelung der Blechtafel ab; hier keinen Verschnittzuschlag einrechnen.

Sheet 20_Maschinen_Stundensaetze
A1: Maschinenstundensätze Deutschland 2026
A2: inkl. Bediener, Energie, Werkzeugverschleiß und Abschreibung – ohne Gewinn und Verwaltungsgemeinkosten.
A4: Verfahren / Maschine | B4: Spanne min [€/h] | C4: Spanne max [€/h] | D4: Startwert [€/h] | E4: Startwert [€/min] | F4: Hinweis
A5: Bearbeitungszentrum 3-Achs | B5: 70 | C5: 100 | D5: 85 | E5: =D5/60 | F5: Standard-Frästeile
A6: Bearbeitungszentrum 5-Achs | B6: 100 | C6: 150 | D6: 115 | E6: =D6/60 | F6: Komplexteile, weniger Aufspannungen
A7: CNC-Drehen 2-Achs | B7: 60 | C7: 90 | D7: 75 | E7: =D7/60 | F7: Futter-/Wellenteile
A8: CNC-Drehen mit angetriebenen Werkzeugen | B8: 85 | C8: 115 | D8: 95 | E8: =D8/60 | F8: Komplettbearbeitung
A9: Langdrehautomat | B9: 70 | C9: 100 | D9: 85 | E9: =D9/60 | F9: Serienkleinteile
A10: Säge / Trennen | B10: 40 | C10: 60 | D10: 50 | E10: =D10/60 | F10: Rohteilzuschnitt
A11: Faserlaser 4–6 kW | B11: 130 | C11: 180 | D11: 150 | E11: =D11/60 | F11: Streuung am Markt 40–300 €/h, Mittelwert ~137 €/h
A12: Stanz-/Nibbelmaschine | B12: 90 | C12: 130 | D12: 110 | E12: =D12/60 | F12: nur bei vorhandenem Werkzeugsatz
A13: Abkantpresse | B13: 70 | C13: 95 | D13: 80 | E13: =D13/60 | F13: Basis für alle Biegekosten
A14: Entgraten / Schleifen manuell | B14: 45 | C14: 65 | D14: 55 | E14: =D14/60 | F14: Handarbeitsplatz
A15: Schweißen MAG/WIG | B15: 55 | C15: 80 | D15: 65 | E15: =D15/60 | F15: inkl. Zusatzwerkstoff-Umlage
A16: Montage / Handarbeitsplatz | B16: 45 | C16: 65 | D16: 55 | E16: =D16/60 | F16: Baugruppenmontage
A17: Messraum / Prüfung | B17: 70 | C17: 95 | D17: 80 | E17: =D17/60 | F17: 3D-Messmaschine inkl. Bediener
A19: Gelb = zentrale Annahme. Diese Werte zuerst mit der eigenen Kostenrechnung abgleichen.
A20: Maschinen in der Vorlage mit den realen Anlagennamen benennen (z. B. 'DMU 50', 'TruLaser 3030').

Sheet 21_Ruestzeiten
A1: Rüstzeiten und Rüstkosten je Los
A2: Rüstkosten werden in Costing über die Losgröße auf das Einzelteil verteilt.
A4: Vorgang | B4: Bezug | C4: Zeit [min] | D4: Stundensatz [€/h] | E4: Rüstkosten [€] | F4: Hinweis
A5: Fräsen – je Aufspannung | B5: je Aufspannung | C5: 45 | D5: 85 | E5: =C5/60*D5 | F5: 3-Achs-BAZ, inkl. Nullpunkt und Erstteil
A6: Fräsen – zusätzlicher Werkzeugwechsel | B6: je Werkzeug | C6: 3 | D6: 85 | E6: =C6/60*D6 | F6: nur bei Werkzeugen außerhalb des Standardsatzes
A7: Drehen – je Aufspannung | B7: je Aufspannung | C7: 30 | D7: 75 | E7: =C7/60*D7 | F7: inkl. Backenwechsel
A8: Sägen – Rohteilzuschnitt | B8: je Los | C8: 10 | D8: 50 | E8: =C8/60*D8
A9: Laserschneiden – je Programm/Tafel | B9: je Tafel | C9: 10 | D9: 150 | E9: =C9/60*D9 | F9: Schachtelung und Materialwechsel
A10: Stanzen – Werkzeugsatz rüsten | B10: je Los | C10: 25 | D10: 110 | E10: =C10/60*D10
A11: Abkanten – Grundrüsten | B11: je Los | C11: 15 | D11: 80 | E11: =C11/60*D11
A12: Abkanten – je zusätzliches Biegewerkzeug | B12: je Werkzeug | C12: 6 | D12: 80 | E12: =C12/60*D12
A13: Schweißvorrichtung einrichten | B13: je Los | C13: 20 | D13: 65 | E13: =C13/60*D13
A14: Pulverbeschichtung – Los anmelden/aufhängen | B14: je Los | C14: 20 | D14: 55 | E14: =C14/60*D14 | F14: zzgl. Mindestlospreis des Beschichters
A15: Messmittel/Prüfplan einrichten | B15: je Los | C15: 15 | D15: 80 | E15: =C15/60*D15
A17: Stundensätze aus Blatt 20 übernommen – bei Änderung dort hier nachziehen.

Sheet 30_Zerspanung_MRR
A1: Zeitspanvolumen und Bohrvorschübe für die Zerspanungsvorlage
A2: Nicht das Spitzen-MRR des Werkzeugherstellers eintragen, sondern den effektiven Wert inkl. Luftschnitten, Werkzeugwechseln und Schlichtanteil (Faustregel: Schruppwert × 0,4–0,5).
A4: Materialklasse | B4: Schruppen min [cm³/min] | C4: Schruppen max [cm³/min] | D4: Schlichten [cm³/min] | E4: Startwert effektiv [cm³/min] | F4: Bohrvorschub [mm/min] | G4: Kosten je cm³ bei 85 €/h | H4: Hinweis
A5: Aluminium | B5: 150 | C5: 400 | D5: 30 | E5: 120 | F5: 500 | G5: =85/60/E5 | H5: 6082/5754, HSC-fähig
A6: Baustahl / Automatenstahl | B6: 40 | C6: 80 | D6: 12 | E6: 35 | F6: 180 | G6: =85/60/E6 | H6: S235, 11SMn30
A7: Vergütungsstahl | B7: 25 | C7: 50 | D7: 8 | E7: 22 | F7: 140 | G7: =85/60/E7 | H7: 42CrMo4, 16MnCr5
A8: Edelstahl | B8: 20 | C8: 40 | D8: 6 | E8: 16 | F8: 110 | G8: =85/60/E8 | H8: 1.4301/1.4404, kühlmittelintensiv
A9: Titan | B9: 8 | C9: 15 | D9: 3 | E9: 7 | F9: 60 | G9: =85/60/E9 | H9: geringe Schnittgeschwindigkeit
A10: Kunststoff | B10: 300 | C10: 600 | D10: 60 | E10: 200 | F10: 600 | G10: =85/60/E10 | H10: POM, PA, PE
A11: Guss | B11: 50 | C11: 90 | D11: 14 | E11: 40 | F11: 200 | G11: =85/60/E11 | H11: GG25, GGG40
A12: Buntmetall | B12: 120 | C12: 300 | D12: 30 | E12: 100 | F12: 400 | G12: =85/60/E12 | H12: Messing, Bronze
A14: Spalte G nur zur Plausibilitätsprüfung: Zerspankosten je cm³ abgetragenem Volumen (3-Achs-BAZ 85 €/h).

Sheet 40_Laser_Schnittwerte
A1: Faserlaser 4–6 kW: Schnittgeschwindigkeiten, Einstechzeiten, Schnittkosten
A2: Bewusst konservativ, weil Costing damit inkl. Beschleunigungs- und Konturverlusten rechnet. Referenz: 6 kW, 10 mm Edelstahl ≈ 2.000–2.500 mm/min; 20 mm Baustahl ≈ 950 mm/min.
A4: Dicke [mm] | B4: S235 (O₂) [mm/min] | C4: 1.4301 (N₂) [mm/min] | D4: AlMg3 (N₂) [mm/min] | E4: Einstechzeit [s] | F4: Schnittkosten S235 [€/m] | G4: Schnittkosten 1.4301 [€/m] | H4: Kosten je Einstich [€]
A5: 1 | B5: 8000 | C5: 25000 | D5: 20000 | E5: 0.3 | F5: =1000/B5*'20_Maschinen_Stundensaetze'!$E$11 | G5: =1000/C5*'20_Maschinen_Stundensaetze'!$E$11 | H5: =E5/60*'20_Maschinen_Stundensaetze'!$E$11
A6: 1.5 | B6: 6500 | C6: 18000 | D6: 14000 | E6: 0.3 | F6: =1000/B6*'20_Maschinen_Stundensaetze'!$E$11 | G6: =1000/C6*'20_Maschinen_Stundensaetze'!$E$11 | H6: =E6/60*'20_Maschinen_Stundensaetze'!$E$11
A7: 2 | B7: 5000 | C7: 12000 | D7: 9500 | E7: 0.3 | F7: =1000/B7*'20_Maschinen_Stundensaetze'!$E$11 | G7: =1000/C7*'20_Maschinen_Stundensaetze'!$E$11 | H7: =E7/60*'20_Maschinen_Stundensaetze'!$E$11
A8: 3 | B8: 3200 | C8: 7000 | D8: 5500 | E8: 0.3 | F8: =1000/B8*'20_Maschinen_Stundensaetze'!$E$11 | G8: =1000/C8*'20_Maschinen_Stundensaetze'!$E$11 | H8: =E8/60*'20_Maschinen_Stundensaetze'!$E$11
A9: 4 | B9: 2600 | C9: 4800 | D9: 3800 | E9: 0.8 | F9: =1000/B9*'20_Maschinen_Stundensaetze'!$E$11 | G9: =1000/C9*'20_Maschinen_Stundensaetze'!$E$11 | H9: =E9/60*'20_Maschinen_Stundensaetze'!$E$11
A10: 5 | B10: 2200 | C10: 3600 | D10: 2800 | E10: 0.8 | F10: =1000/B10*'20_Maschinen_Stundensaetze'!$E$11 | G10: =1000/C10*'20_Maschinen_Stundensaetze'!$E$11 | H10: =E10/60*'20_Maschinen_Stundensaetze'!$E$11
A11: 6 | B11: 1900 | C11: 2900 | D11: 2200 | E11: 0.8 | F11: =1000/B11*'20_Maschinen_Stundensaetze'!$E$11 | G11: =1000/C11*'20_Maschinen_Stundensaetze'!$E$11 | H11: =E11/60*'20_Maschinen_Stundensaetze'!$E$11
A12: 8 | B12: 1500 | C12: 2100 | D12: 1500 | E12: 1.5 | F12: =1000/B12*'20_Maschinen_Stundensaetze'!$E$11 | G12: =1000/C12*'20_Maschinen_Stundensaetze'!$E$11 | H12: =E12/60*'20_Maschinen_Stundensaetze'!$E$11
A13: 10 | B13: 1250 | C13: 1600 | D13: 1000 | E13: 1.5 | F13: =1000/B13*'20_Maschinen_Stundensaetze'!$E$11 | G13: =1000/C13*'20_Maschinen_Stundensaetze'!$E$11 | H13: =E13/60*'20_Maschinen_Stundensaetze'!$E$11
A14: 12 | B14: 1000 | C14: 1150 | D14: 700 | E14: 2.5 | F14: =1000/B14*'20_Maschinen_Stundensaetze'!$E$11 | G14: =1000/C14*'20_Maschinen_Stundensaetze'!$E$11 | H14: =E14/60*'20_Maschinen_Stundensaetze'!$E$11
A15: 15 | B15: 800 | C15: 800 | D15: – | E15: 2.5 | F15: =1000/B15*'20_Maschinen_Stundensaetze'!$E$11 | G15: =1000/C15*'20_Maschinen_Stundensaetze'!$E$11 | H15: =E15/60*'20_Maschinen_Stundensaetze'!$E$11
A16: 20 | B16: 600 | C16: – | D16: – | E16: 4 | F16: =1000/B16*'20_Maschinen_Stundensaetze'!$E$11 | G16: – | H16: =E16/60*'20_Maschinen_Stundensaetze'!$E$11
A18: Schnittkosten = Schnittzeit × Laser-Minutensatz aus Blatt 20 (Zeile 'Faserlaser 4–6 kW').
A19: Stanzen alternativ: 0,04–0,08 € je Standardhub, 0,15–0,30 € je Umformwerkzeug (Durchzug, Kieme).

Sheet 41_Biegen
A1: Biegen / Abkanten – Zeiten und Kosten je Biegung
A2: Kalkulationsbasis Abkantpresse 80 €/h. Mengeneffekte über die Losgröße abbilden, nicht über kleinere Biegepreise.
A4: Teileklasse | B4: Kantenlänge | C4: Blechdicke | D4: Zeit je Biegung [min] | E4: Kosten je Biegung [€] | F4: Handling je Teil [min] | G4: Handling je Teil [€] | H4: Hinweis
A5: klein | B5: < 500 mm | C5: 1–3 mm | D5: 0.15 | E5: =D5*'20_Maschinen_Stundensaetze'!$E$13 | F5: 0.2 | G5: =F5*'20_Maschinen_Stundensaetze'!$E$13 | H5: Einmannbedienung
A6: mittel | B6: 500–1.500 mm | C6: 1–4 mm | D6: 0.26 | E6: =D6*'20_Maschinen_Stundensaetze'!$E$13 | F6: 0.3 | G6: =F6*'20_Maschinen_Stundensaetze'!$E$13 | H6: Standardfall
A7: groß | B7: 1.500–2.000 mm | C7: 2–6 mm | D7: 0.45 | E7: =D7*'20_Maschinen_Stundensaetze'!$E$13 | F7: 0.45 | G7: =F7*'20_Maschinen_Stundensaetze'!$E$13 | H7: Anlagehilfe nötig
A8: sehr groß / 2-Mann | B8: > 2.000 mm | C8: 3–8 mm | D8: 0.7 | E8: =D8*'20_Maschinen_Stundensaetze'!$E$13 | F8: 0.8 | G8: =F8*'20_Maschinen_Stundensaetze'!$E$13 | H8: zwei Bediener, Kosten verdoppeln sich faktisch
A9: Sonderfall | B9: enger Radius / schlecht zugänglich | C9: beliebig | D9: 0.4 | E9: =D9*'20_Maschinen_Stundensaetze'!$E$13 | F9: 0.4 | G9: =F9*'20_Maschinen_Stundensaetze'!$E$13 | H9: Aufschlag 30–60 % auf Standardzeit
A10: Hem / Falz | B10: < 1.000 mm | C10: 1–2 mm | D10: 0.35 | E10: =D10*'20_Maschinen_Stundensaetze'!$E$13 | F10: 0.3 | G10: =F10*'20_Maschinen_Stundensaetze'!$E$13 | H10: zwei Arbeitsgänge
A12: Ab Losgröße 50–100 sinken die Stückkosten je Biegung praxisüblich um 20–40 % – das entsteht in Costing automatisch durch die Verteilung der Rüstkosten.

Sheet 50_Custom_Operationen
A1: Benutzerdefinierte Operationen (Register 'Benutzerdefiniert')
A2: Kosten ohne Geometriebezug. In der Vorlage an eine Materialklasse oder an 'alle Materialien' hängen.
A4: Operation | B4: Einheit | C4: min | D4: max | E4: Startwert | F4: Mindestlospreis [€] | G4: Hinweis
A5: Pulverbeschichten | B5: €/m² | C5: 22 | D5: 35 | E5: 28 | F5: 55 | G5: RAL-Standard, einfarbig
A6: Nasslackieren | B6: €/m² | C6: 30 | D6: 55 | E6: 40 | F6: 80 | G6: 2K, inkl. Grundierung
A7: Eloxieren natur E6/EV1 | B7: €/m² | C7: 25 | D7: 45 | E7: 32 | F7: 60 | G7: nur Aluminium
A8: Verzinken galvanisch | B8: €/kg | C8: 0.8 | D8: 1.5 | E8: 1.1 | F8: 30 | G8: blau-/gelbchromatiert
A9: Feuerverzinken | B9: €/kg | C9: 0.55 | D9: 0.95 | E9: 0.75 | F9: 60 | G9: ab ca. 3 mm Blechdicke
A10: Brünieren | B10: €/kg | C10: 0.6 | D10: 1.1 | E10: 0.85 | F10: 30
A11: Entgraten manuell | B11: €/Teil | C11: 0.45 | D11: 2.75 | E11: 1 | F11: 0 | G11: 0,5–3 min bei 55 €/h
A12: Gleitschleifen | B12: €/kg | C12: 0.8 | D12: 1.6 | E12: 1.1 | F12: 40 | G12: Serienteile
A13: Gewinde M4–M12 schneiden | B13: €/Gewinde | C13: 0.1 | D13: 0.3 | E13: 0.18 | F13: 0 | G13: auf der Maschine
A14: Senkung | B14: €/Senkung | C14: 0.05 | D14: 0.12 | E14: 0.08 | F14: 0
A15: Einpressmutter/-bolzen setzen | B15: €/Stück | C15: 0.25 | D15: 0.55 | E15: 0.4 | F15: 0 | G15: inkl. Normteil
A16: Lasergravur / Beschriftung | B16: €/Teil | C16: 0.5 | D16: 2 | E16: 1 | F16: 0 | G16: Typenschildinhalt
A17: Wärmebehandlung Vergüten | B17: €/kg | C17: 1.2 | D17: 2.5 | E17: 1.7 | F17: 80
A18: Erstmusterprüfbericht (EMPB) | B18: €/Los | C18: 60 | D18: 150 | E18: 95 | F18: 0 | G18: nur bei Erstteil
A19: Endprüfung / Messprotokoll | B19: €/Teil | C19: 2 | D19: 8 | E19: 4 | F19: 0 | G19: abhängig von Merkmalanzahl
A20: Verpackung | B20: €/Teil | C20: 1.5 | D20: 6 | E20: 2.5 | F20: 0 | G20: Kartonage/Palette
A22: Oberflächenkosten je m² rechnet Costing über die vom Modell erkannte Oberfläche – Mindestlospreise sind in Costing nicht direkt abbildbar und gehören in den Aufschlag oder ins Angebot.

Sheet 60_Aufschlaege
A1: Aufschläge und Kalkulationszuschläge
A2: In Costing im Task-Fenster je Teil als Aufschlag (positiv) bzw. Rabatt (negativ) gesetzt.
A4: Position | B4: Wert | C4: Bezug | D4: Hinweis
A5: Ausschuss / Nacharbeit | B5: 0.02 | C5: auf Herstellkosten | D5: 1–3 %, je nach Prozessstabilität
A6: Werkzeugverschleiß | B6: 0 | C6: im Stundensatz enthalten | D6: nicht doppelt aufschlagen
A7: Verwaltungs-/Vertriebsgemeinkosten | B7: 0.12 | C7: auf Herstellkosten | D7: 8–15 % je nach Overhead
A8: Gewinn Einzelteil/Prototyp | B8: 0.14 | C8: auf Selbstkosten | D8: 12–15 %
A9: Gewinn Serie | B9: 0.06 | C9: auf Selbstkosten | D9: 5–8 %
A10: Materialteuerungszuschlag | B10: 0.03 | C10: auf Materialkosten | D10: nur bei langen Angebotsbindungen
A11: Mengenrabatt ab 100 Stück | B11: -0.08 | C11: auf Gesamtkosten | D11: als negativer Aufschlag eintragen
A13: Beispielrechnung Einzelteil
A14: Herstellkosten (aus Costing) | B14: 100
A15: + Ausschuss | B15: =B14*B5
A16: + Verwaltung / Vertrieb | B16: =B14*B7
A17: =Selbstkosten | B17: =SUM(B14:B16)
A18: + Gewinn Einzelteil | B18: =B17*B8
A19: =Angebotspreis | B19: =B17+B18
A21: Die Beispielrechnung zeigt die Reihenfolge – Costing selbst liefert die Herstellkosten in B14.
